{"cameraMode":{"drawMode":0,"name":"Shaded","section":"Shading Mode"},"sceneLighting":true,"audioPlay":false,"sceneViewState":{"m_AlwaysRefresh":false,"showFog":true,"showSkybox":true,"showFlares":true,"showImageEffects":true,"showParticleSystems":true,"showVisualEffectGraphs":true,"m_FxEnabled":false},"in2DMode":false,"pivot":{"x":924.703857421875,"y":139.88726806640626,"z":-1691.2996826171875},"rotation":{"x":-0.47087740898132326,"y":0.410241961479187,"z":-0.26262199878692629,"w":-0.7356266975402832},"size":1.1722668409347535,"orthographic":false}